ZOCallable/ZOCallable.py
ZOCallable/__init__.py
ZOCallable/functions.py
ZOCallable/plot.py
ZOCallable-1.0.2.dist-info/LICENSE
ZOCallable-1.0.2.dist-info/METADATA
ZOCallable-1.0.2.dist-info/WHEEL
ZOCallable-1.0.2.dist-info/top_level.txt
ZOCallable-1.0.2.dist-info/RECORD
