Metadata-Version: 2.2
Name: ZOCallable
Version: 1.0.2
Summary: ZOCallable is a library defining multiple functions f : [0, 1] -> R, and satisfying the condition f(0) = 0 and f(1) = 1. They can be used as transitions.
Home-page: https://github.com/Tanguy-ddv/pygame-arts
Author: Tanguy Dugas du Villard
Classifier: Programming Language :: Python :: 3
Classifier: Operating System :: OS Independent
Classifier: Topic :: Scientific/Engineering :: Mathematics
Requires-Python: >=3.6
License-File: LICENSE
Requires-Dist: numpy
Dynamic: author
Dynamic: classifier
Dynamic: description
Dynamic: description-content-type
Dynamic: home-page
Dynamic: requires-dist
Dynamic: requires-python
Dynamic: summary
